SnakeRL-0.0.1.dist-info/METADATA
SnakeRL-0.0.1.dist-info/RECORD
SnakeRL-0.0.1.dist-info/WHEEL
SnakeRL-0.0.1.dist-info/top_level.txt
snakerl/__init__.py
