Metadata-Version: 2.1
Name: SnakeRL
Version: 0.0.1
Summary: A Multi Agent Reinforcement Learning environment
Home-page: https://github.com/vrishank97/SnakeRL
Author: Vrishank Bhardwaj
Author-email: vrishank1997@gmail.com
License: UNKNOWN
Platform: UNKNOWN
Classifier: Programming Language :: Python :: 3
Classifier: License :: OSI Approved :: MIT License
Classifier: Operating System :: OS Independent
